image_blur.v
module image_blur(
    input clk,
    input reset,
    input start,
    input [7:0] image_in,       // Input pixel data (1 byte per clock)
    output reg [7:0] image_out, // Output pixel data (1 byte per clock)
    output reg done             // Done signal
);

parameter WIDTH = 20;
parameter HEIGHT = 12;
parameter KERNEL_SIZE = 3;

reg[7:0] inputImage[0 : WIDTH*HEIGHT*3-1]; // Input/output image
reg[7:0] outputImage[0 : WIDTH*HEIGHT*3-1]; // Output image
reg[7:0] kernel[0 : KERNEL_SIZE*KERNEL_SIZE-1]; // Kernel coefficients

integer row, col, color_cycle; // Row and column counters
reg[31:0] acc_R, acc_G, acc_B; // Accumulators for RGB channels
reg[31:0] divider; // Divider for normalization

// FSM states
reg[2:0] state = IDLE;
parameter IDLE = 0, LOAD_IMAGE = 1, PROCESS_PIXEL = 2, WRITE_IMAGE = 3, DONE = 4;

// Initialization
always @(posedge clk or posedge reset) begin
    if (reset) begin
        done <= 0;
        row <= 0;
        col <= 0;
        color_cycle <= 0;
        acc_R <= 0;
        acc_G <= 0;
        acc_B <= 0;
        divider <= 0;

        // Initialize kernel with gaussian blur coefficients
        kernel[0] <= 1; kernel[1] <= 2; kernel[2] <= 1;
        kernel[3] <= 2; kernel[4] <= 4; kernel[5] <= 2;
        kernel[6] <= 1; kernel[7] <= 2; kernel[8] <= 1;
    end else begin
        case (state)
            IDLE: begin
                $display("Waiting for start signal\n");
                if (start) begin
                    state <= LOAD_IMAGE;
                    $display("Loading input image");
                end
            end
            LOAD_IMAGE: begin
                // Simulate loading image into memory (external interface)
                // In real design, connect image_in to external memory
                if (row < HEIGHT && col < WIDTH) begin
                    $display("Row: %2d, Col: %2d, Color cycle: %2d", row, col, color_cycle);
                    case (color_cycle)
                        0: inputImage[(row * WIDTH + col) * 3 + 0] <= image_in; // Red
                        1: inputImage[(row * WIDTH + col) * 3 + 1] <= image_in; // Green
                        2: begin
                            inputImage[(row * WIDTH + col) * 3 + 2] <= image_in; // Blue
                            col <= col + 1; // Move to the next column after Blue
                            if (col == WIDTH-1) begin
                                col <= 0;       // Reset column
                                row <= row + 1; // Move to the next row
                            end
                        end
                    endcase
                    color_cycle <= (color_cycle + 1) % 3;
                end else begin
                    // Display all input image data
                    for (integer i = 0; i < WIDTH*HEIGHT*3; i = i + 1) begin
                        $display("Input image[%2d]: %2X", i, inputImage[i]);
                    end
                    $display("Finished loading input image\n");
                    row <= 0;
                    col <= 0;
                    color_cycle <= 0;
                    state <= PROCESS_PIXEL;
                    $display("Processing image");
                end
            end
            PROCESS_PIXEL: begin
                // Apply kernel to calculate new RGB values
                // Boundary handling
                if (row < HEIGHT && col < WIDTH) begin
                    $display("Row: %2d, Col: %2d", row, col);
                    acc_R = 0;
                    acc_G = 0;
                    acc_B = 0;
                    divider = 0; // Normalization factor (sum of kernel)
                    for (integer ki = 0; ki < KERNEL_SIZE; ki++) begin
                        for (integer kj = 0; kj < KERNEL_SIZE; kj++) begin
                            // $display("Row: %d, Col: %d\n", row+ki-1, col+kj-1);
                            if (row+ki-1 >= 0 && row+ki-1 <= HEIGHT-1 && col+kj-1 >= 0 && col+kj-1 <= WIDTH-1) begin
                                acc_R = acc_R + kernel[ki*KERNEL_SIZE+kj] * inputImage[((row+ki-1)*WIDTH + (col+kj-1))*3];
                                acc_G = acc_G + kernel[ki*KERNEL_SIZE+kj] * inputImage[((row+ki-1)*WIDTH + (col+kj-1))*3+1];
                                acc_B = acc_B + kernel[ki*KERNEL_SIZE+kj] * inputImage[((row+ki-1)*WIDTH + (col+kj-1))*3+2];
                                divider = divider + kernel[ki*KERNEL_SIZE+kj];
                            end
                        end
                    end
                    // Normalize the result
                    outputImage[(row*WIDTH + col) * 3] = acc_R / divider;
                    outputImage[(row*WIDTH + col) * 3 + 1] = acc_G / divider;
                    outputImage[(row*WIDTH + col) * 3 + 2] = acc_B / divider;

                    col <= col + 1; // Move to the next column after Blue
                    if (col == WIDTH-1) begin
                        col <= 0;       // Reset column
                        row <= row + 1; // Move to the next row
                    end
                end else begin
                    // Display all output image data
                    for (integer i = 0; i < WIDTH*HEIGHT*3; i = i + 1) begin
                        $display("Output image[%2d]: %2X", i, outputImage[i]);
                    end
                    $display("Finished processing image\n");
                    state <= WRITE_IMAGE;
                    done <= 1;
                    row <= 0;
                    col <= 0;
                    $display("Writing output image");
                end
            end
            WRITE_IMAGE: begin
                // Write back processed image
                if (row < HEIGHT && col < WIDTH) begin
                    $display("Row: %2d, Col: %2d, Color cycle: %2d", row, col, color_cycle);
                    case (color_cycle)
                        0: image_out = outputImage[(row * WIDTH + col) * 3 + 0]; // Red
                        1: image_out = outputImage[(row * WIDTH + col) * 3 + 1]; // Green
                        2: begin
                            image_out = outputImage[(row * WIDTH + col) * 3 + 2]; // Blue
                            col <= col + 1; // Move to the next column after Blue
                            if (col == WIDTH-1) begin
                                col <= 0;       // Reset column
                                row <= row + 1; // Move to the next row
                            end
                        end
                    endcase
                    color_cycle <= (color_cycle + 1) % 3;
                end else begin
                    $display("Finished writing output image\n");
                    state <= DONE;
                end
            end
            DONE: begin
                // Output is complete
            end
        endcase
    end
end

endmodule

image_blur_TB.v
`timescale 1ns/1ps

module image_blur_TB();

parameter WIDTH = 20;
parameter HEIGHT = 12;

reg clk = 1'b0;
reg reset = 1'b1;
reg start = 1'b0;
reg [7:0] image_in = 1'b0;
wire [7:0] image_out;
wire done;

reg [7:0] image_memory [0:WIDTH*HEIGHT*3-1];
integer i;

integer out_file;

image_blur DUT(.clk(clk), .reset(reset), .start(start), .image_in(image_in), .image_out(image_out), .done(done));

always    
    #10 clk = ~clk;

initial begin
    $dumpfile("image_blur.vcd");
    $dumpvars(0, image_blur_TB);

    $readmemh("input.hex", image_memory);
    
    #20
    reset = 0;
    start = 1;

    for (i = 0; i < WIDTH * HEIGHT * 3; i = i + 1) begin
        @(posedge clk);
        image_in <= image_memory[i];
    end

    // $display("Done\n");

    wait(done)
    @(posedge clk);

    // $display("Writing output to output.hex\n");

    out_file = $fopen("output.hex", "w");
    for (i = 0; i < WIDTH * HEIGHT * 3; i = i + 1) begin
        @(posedge clk);
        $fwrite(out_file, "%02X\n", image_out);
    end
    $fclose(out_file);

    $finish();
end

endmodule

image_blur.vcd
$date
	Fri Nov 29 22:33:03 2024
$end
$version
	Icarus Verilog
$end
$timescale
	1ps
$end
$scope module image_blur_TB $end
$var wire 8 ! image_out [7:0] $end
$var wire 1 " done $end
$var parameter 32 # HEIGHT $end
$var parameter 32 $ WIDTH $end
$var reg 1 % clk $end
$var reg 8 & image_in [7:0] $end
$var reg 1 ' reset $end
$var reg 1 ( start $end
$var integer 32 ) i [31:0] $end
$var integer 32 * out_file [31:0] $end
$scope module DUT $end
$var wire 1 % clk $end
$var wire 8 + image_in [7:0] $end
$var wire 1 ' reset $end
$var wire 1 ( start $end
$var parameter 32 , DONE $end
$var parameter 32 - HEIGHT $end
$var parameter 32 . IDLE $end
$var parameter 32 / KERNEL_SIZE $end
$var parameter 32 0 LOAD_IMAGE $end
$var parameter 32 1 PROCESS_PIXEL $end
$var parameter 32 2 WIDTH $end
$var parameter 32 3 WRITE_IMAGE $end
$var reg 32 4 acc_B [31:0] $end
$var reg 32 5 acc_G [31:0] $end
$var reg 32 6 acc_R [31:0] $end
$var reg 32 7 divider [31:0] $end
$var reg 1 " done $end
$var reg 8 8 image_out [7:0] $end
$var reg 3 9 state [2:0] $end
$var integer 32 : col [31:0] $end
$var integer 32 ; color_cycle [31:0] $end
$var integer 32 < row [31:0] $end
$scope begin $ivl_for_loop0 $end
$var integer 32 = i [31:0] $end
$upscope $end
$scope begin $ivl_for_loop1 $end
$var integer 32 > ki [31:0] $end
$scope begin $ivl_for_loop2 $end
$var integer 32 ? kj [31:0] $end
$upscope $end
$upscope $end
$scope begin $ivl_for_loop3 $end
$var integer 32 @ i [31:0] $end
$upscope $end
$upscope $end
$upscope $end
$enddefinitions $end
$comment Show the parameter values. $end
$dumpall
b11 3
b10100 2
b10 1
b1 0
b11 /
b0 .
b1100 -
b100 ,
b10100 $
b1100 #
$end
#0
$dumpvars
bx @
bx ?
bx >
bx =
b0 <
b0 ;
b0 :
b0 9
bx 8
b0 7
b0 6
b0 5
b0 4
b0 +
bx *
bx )
0(
1'
b0 &
0%
0"
bx !
$end
#10000
1%
#20000
0%
b0 )
1(
0'
#30000
b1 9
b1001101 &
b1001101 +
b1 )
1%
#40000
0%
#50000
b1 ;
b1101101 &
b1101101 +
b10 )
1%
#60000
0%
#70000
b10 ;
b11110011 &
b11110011 +
b11 )
1%
#80000
0%
#90000
b0 ;
b1 :
b1001101 &
b1001101 +
b100 )
1%
#100000
0%
#110000
b1 ;
b1101101 &
b1101101 +
b101 )
1%
#120000
0%
#130000
b10 ;
b11110011 &
b11110011 +
b110 )
1%
#140000
0%
#150000
b0 ;
b10 :
b1001101 &
b1001101 +
b111 )
1%
#160000
0%
#170000
b1 ;
b1101101 &
b1101101 +
b1000 )
1%
#180000
0%
#190000
b10 ;
b11110011 &
b11110011 +
b1001 )
1%
#200000
0%
#210000
b0 ;
b11 :
b11101101 &
b11101101 +
b1010 )
1%
#220000
0%
#230000
b1 ;
b11100 &
b11100 +
b1011 )
1%
#240000
0%
#250000
b10 ;
b100100 &
b100100 +
b1100 )
1%
#260000
0%
#270000
b0 ;
b100 :
b11101101 &
b11101101 +
b1101 )
1%
#280000
0%
#290000
b1 ;
b11100 &
b11100 +
b1110 )
1%
#300000
0%
#310000
b10 ;
b100100 &
b100100 +
b1111 )
1%
#320000
0%
#330000
b0 ;
b101 :
b11101101 &
b11101101 +
b10000 )
1%
#340000
0%
#350000
b1 ;
b11100 &
b11100 +
b10001 )
1%
#360000
0%
#370000
b10 ;
b100100 &
b100100 +
b10010 )
1%
#380000
0%
#390000
b0 ;
b110 :
b10110100 &
b10110100 +
b10011 )
1%
#400000
0%
#410000
b1 ;
b10100 )
1%
#420000
0%
#430000
b10 ;
b10101 )
1%
#440000
0%
#450000
b0 ;
b111 :
b10110 )
1%
#460000
0%
#470000
b1 ;
b10111 )
1%
#480000
0%
#490000
b10 ;
b11000 )
1%
#500000
0%
#510000
b0 ;
b1000 :
b11111111 &
b11111111 +
b11001 )
1%
#520000
0%
#530000
b1 ;
b11110010 &
b11110010 +
b11010 )
1%
#540000
0%
#550000
b10 ;
b0 &
b0 +
b11011 )
1%
#560000
0%
#570000
b0 ;
b1001 :
b11111111 &
b11111111 +
b11100 )
1%
#580000
0%
#590000
b1 ;
b11110010 &
b11110010 +
b11101 )
1%
#600000
0%
#610000
b10 ;
b0 &
b0 +
b11110 )
1%
#620000
0%
#630000
b0 ;
b1010 :
b11111111 &
b11111111 +
b11111 )
1%
#640000
0%
#650000
b1 ;
b11110010 &
b11110010 +
b100000 )
1%
#660000
0%
#670000
b10 ;
b0 &
b0 +
b100001 )
1%
#680000
0%
#690000
b0 ;
b1011 :
b11111111 &
b11111111 +
b100010 )
1%
#700000
0%
#710000
b1 ;
b11110010 &
b11110010 +
b100011 )
1%
#720000
0%
#730000
b10 ;
b0 &
b0 +
b100100 )
1%
#740000
0%
#750000
b0 ;
b1100 :
b11100101 &
b11100101 +
b100101 )
1%
#760000
0%
#770000
b1 ;
b10101010 &
b10101010 +
b100110 )
1%
#780000
0%
#790000
b10 ;
b1111010 &
b1111010 +
b100111 )
1%
#800000
0%
#810000
b0 ;
b1101 :
b11100101 &
b11100101 +
b101000 )
1%
#820000
0%
#830000
b1 ;
b10101010 &
b10101010 +
b101001 )
1%
#840000
0%
#850000
b10 ;
b1111010 &
b1111010 +
b101010 )
1%
#860000
0%
#870000
b0 ;
b1110 :
b0 &
b0 +
b101011 )
1%
#880000
0%
#890000
b1 ;
b10110111 &
b10110111 +
b101100 )
1%
#900000
0%
#910000
b10 ;
b11101111 &
b11101111 +
b101101 )
1%
#920000
0%
#930000
b0 ;
b1111 :
b0 &
b0 +
b101110 )
1%
#940000
0%
#950000
b1 ;
b10110111 &
b10110111 +
b101111 )
1%
#960000
0%
#970000
b10 ;
b11101111 &
b11101111 +
b110000 )
1%
#980000
0%
#990000
b0 ;
b10000 :
b0 &
b0 +
b110001 )
1%
#1000000
0%
#1010000
b1 ;
b10110111 &
b10110111 +
b110010 )
1%
#1020000
0%
#1030000
b10 ;
b11101111 &
b11101111 +
b110011 )
1%
#1040000
0%
#1050000
b0 ;
b10001 :
b11111111 &
b11111111 +
b110100 )
1%
#1060000
0%
#1070000
b1 ;
b10100011 &
b10100011 +
b110101 )
1%
#1080000
0%
#1090000
b10 ;
b10110001 &
b10110001 +
b110110 )
1%
#1100000
0%
#1110000
b0 ;
b10010 :
b11111111 &
b11111111 +
b110111 )
1%
#1120000
0%
#1130000
b1 ;
b10100011 &
b10100011 +
b111000 )
1%
#1140000
0%
#1150000
b10 ;
b10110001 &
b10110001 +
b111001 )
1%
#1160000
0%
#1170000
b0 ;
b10011 :
b11111111 &
b11111111 +
b111010 )
1%
#1180000
0%
#1190000
b1 ;
b10100011 &
b10100011 +
b111011 )
1%
#1200000
0%
#1210000
b10 ;
b10110001 &
b10110001 +
b111100 )
1%
#1220000
0%
#1230000
b0 ;
b1 <
b0 :
b1001101 &
b1001101 +
b111101 )
1%
#1240000
0%
#1250000
b1 ;
b1101101 &
b1101101 +
b111110 )
1%
#1260000
0%
#1270000
b10 ;
b11110011 &
b11110011 +
b111111 )
1%
#1280000
0%
#1290000
b0 ;
b1 :
b1001101 &
b1001101 +
b1000000 )
1%
#1300000
0%
#1310000
b1 ;
b1101101 &
b1101101 +
b1000001 )
1%
#1320000
0%
#1330000
b10 ;
b11110011 &
b11110011 +
b1000010 )
1%
#1340000
0%
#1350000
b0 ;
b10 :
b1001101 &
b1001101 +
b1000011 )
1%
#1360000
0%
#1370000
b1 ;
b1101101 &
b1101101 +
b1000100 )
1%
#1380000
0%
#1390000
b10 ;
b11110011 &
b11110011 +
b1000101 )
1%
#1400000
0%
#1410000
b0 ;
b11 :
b1101111 &
b1101111 +
b1000110 )
1%
#1420000
0%
#1430000
b1 ;
b110001 &
b110001 +
b1000111 )
1%
#1440000
0%
#1450000
b10 ;
b10011000 &
b10011000 +
b1001000 )
1%
#1460000
0%
#1470000
b0 ;
b100 :
b11101101 &
b11101101 +
b1001001 )
1%
#1480000
0%
#1490000
b1 ;
b11100 &
b11100 +
b1001010 )
1%
#1500000
0%
#1510000
b10 ;
b100100 &
b100100 +
b1001011 )
1%
#1520000
0%
#1530000
b0 ;
b101 :
b11101101 &
b11101101 +
b1001100 )
1%
#1540000
0%
#1550000
b1 ;
b11100 &
b11100 +
b1001101 )
1%
#1560000
0%
#1570000
b10 ;
b100100 &
b100100 +
b1001110 )
1%
#1580000
0%
#1590000
b0 ;
b110 :
b11101101 &
b11101101 +
b1001111 )
1%
#1600000
0%
#1610000
b1 ;
b11100 &
b11100 +
b1010000 )
1%
#1620000
0%
#1630000
b10 ;
b100100 &
b100100 +
b1010001 )
1%
#1640000
0%
#1650000
b0 ;
b111 :
b10110100 &
b10110100 +
b1010010 )
1%
#1660000
0%
#1670000
b1 ;
b1010011 )
1%
#1680000
0%
#1690000
b10 ;
b1010100 )
1%
#1700000
0%
#1710000
b0 ;
b1000 :
b11111111 &
b11111111 +
b1010101 )
1%
#1720000
0%
#1730000
b1 ;
b11110010 &
b11110010 +
b1010110 )
1%
#1740000
0%
#1750000
b10 ;
b0 &
b0 +
b1010111 )
1%
#1760000
0%
#1770000
b0 ;
b1001 :
b11111111 &
b11111111 +
b1011000 )
1%
#1780000
0%
#1790000
b1 ;
b11110010 &
b11110010 +
b1011001 )
1%
#1800000
0%
#1810000
b10 ;
b0 &
b0 +
b1011010 )
1%
#1820000
0%
#1830000
b0 ;
b1010 :
b11111111 &
b11111111 +
b1011011 )
1%
#1840000
0%
#1850000
b1 ;
b11110010 &
b11110010 +
b1011100 )
1%
#1860000
0%
#1870000
b10 ;
b0 &
b0 +
b1011101 )
1%
#1880000
0%
#1890000
b0 ;
b1011 :
b11111111 &
b11111111 +
b1011110 )
1%
#1900000
0%
#1910000
b1 ;
b11110010 &
b11110010 +
b1011111 )
1%
#1920000
0%
#1930000
b10 ;
b0 &
b0 +
b1100000 )
1%
#1940000
0%
#1950000
b0 ;
b1100 :
b11100101 &
b11100101 +
b1100001 )
1%
#1960000
0%
#1970000
b1 ;
b10101010 &
b10101010 +
b1100010 )
1%
#1980000
0%
#1990000
b10 ;
b1111010 &
b1111010 +
b1100011 )
1%
#2000000
0%
#2010000
b0 ;
b1101 :
b0 &
b0 +
b1100100 )
1%
#2020000
0%
#2030000
b1 ;
b10110111 &
b10110111 +
b1100101 )
1%
#2040000
0%
#2050000
b10 ;
b11101111 &
b11101111 +
b1100110 )
1%
#2060000
0%
#2070000
b0 ;
b1110 :
b0 &
b0 +
b1100111 )
1%
#2080000
0%
#2090000
b1 ;
b10110111 &
b10110111 +
b1101000 )
1%
#2100000
0%
#2110000
b10 ;
b11101111 &
b11101111 +
b1101001 )
1%
#2120000
0%
#2130000
b0 ;
b1111 :
b0 &
b0 +
b1101010 )
1%
#2140000
0%
#2150000
b1 ;
b10110111 &
b10110111 +
b1101011 )
1%
#2160000
0%
#2170000
b10 ;
b11101111 &
b11101111 +
b1101100 )
1%
#2180000
0%
#2190000
b0 ;
b10000 :
b1101111 &
b1101111 +
b1101101 )
1%
#2200000
0%
#2210000
b1 ;
b110001 &
b110001 +
b1101110 )
1%
#2220000
0%
#2230000
b10 ;
b10011000 &
b10011000 +
b1101111 )
1%
#2240000
0%
#2250000
b0 ;
b10001 :
b11111111 &
b11111111 +
b1110000 )
1%
#2260000
0%
#2270000
b1 ;
b10100011 &
b10100011 +
b1110001 )
1%
#2280000
0%
#2290000
b10 ;
b10110001 &
b10110001 +
b1110010 )
1%
#2300000
0%
#2310000
b0 ;
b10010 :
b11111111 &
b11111111 +
b1110011 )
1%
#2320000
0%
#2330000
b1 ;
b10100011 &
b10100011 +
b1110100 )
1%
#2340000
0%
#2350000
b10 ;
b10110001 &
b10110001 +
b1110101 )
1%
#2360000
0%
#2370000
b0 ;
b10011 :
b11111111 &
b11111111 +
b1110110 )
1%
#2380000
0%
#2390000
b1 ;
b10100011 &
b10100011 +
b1110111 )
1%
#2400000
0%
#2410000
b10 ;
b10110001 &
b10110001 +
b1111000 )
1%
#2420000
0%
#2430000
b0 ;
b10 <
b0 :
b1001101 &
b1001101 +
b1111001 )
1%
#2440000
0%
#2450000
b1 ;
b1101101 &
b1101101 +
b1111010 )
1%
#2460000
0%
#2470000
b10 ;
b11110011 &
b11110011 +
b1111011 )
1%
#2480000
0%
#2490000
b0 ;
b1 :
b1001101 &
b1001101 +
b1111100 )
1%
#2500000
0%
#2510000
b1 ;
b1101101 &
b1101101 +
b1111101 )
1%
#2520000
0%
#2530000
b10 ;
b11110011 &
b11110011 +
b1111110 )
1%
#2540000
0%
#2550000
b0 ;
b10 :
b1001101 &
b1001101 +
b1111111 )
1%
#2560000
0%
#2570000
b1 ;
b1101101 &
b1101101 +
b10000000 )
1%
#2580000
0%
#2590000
b10 ;
b11110011 &
b11110011 +
b10000001 )
1%
#2600000
0%
#2610000
b0 ;
b11 :
b1101111 &
b1101111 +
b10000010 )
1%
#2620000
0%
#2630000
b1 ;
b110001 &
b110001 +
b10000011 )
1%
#2640000
0%
#2650000
b10 ;
b10011000 &
b10011000 +
b10000100 )
1%
#2660000
0%
#2670000
b0 ;
b100 :
b1101111 &
b1101111 +
b10000101 )
1%
#2680000
0%
#2690000
b1 ;
b110001 &
b110001 +
b10000110 )
1%
#2700000
0%
#2710000
b10 ;
b10011000 &
b10011000 +
b10000111 )
1%
#2720000
0%
#2730000
b0 ;
b101 :
b11101101 &
b11101101 +
b10001000 )
1%
#2740000
0%
#2750000
b1 ;
b11100 &
b11100 +
b10001001 )
1%
#2760000
0%
#2770000
b10 ;
b100100 &
b100100 +
b10001010 )
1%
#2780000
0%
#2790000
b0 ;
b110 :
b11101101 &
b11101101 +
b10001011 )
1%
#2800000
0%
#2810000
b1 ;
b11100 &
b11100 +
b10001100 )
1%
#2820000
0%
#2830000
b10 ;
b100100 &
b100100 +
b10001101 )
1%
#2840000
0%
#2850000
b0 ;
b111 :
b11101101 &
b11101101 +
b10001110 )
1%
#2860000
0%
#2870000
b1 ;
b11100 &
b11100 +
b10001111 )
1%
#2880000
0%
#2890000
b10 ;
b100100 &
b100100 +
b10010000 )
1%
#2900000
0%
#2910000
b0 ;
b1000 :
b11101101 &
b11101101 +
b10010001 )
1%
#2920000
0%
#2930000
b1 ;
b11100 &
b11100 +
b10010010 )
1%
#2940000
0%
#2950000
b10 ;
b100100 &
b100100 +
b10010011 )
1%
#2960000
0%
#2970000
b0 ;
b1001 :
b11101101 &
b11101101 +
b10010100 )
1%
#2980000
0%
#2990000
b1 ;
b11100 &
b11100 +
b10010101 )
1%
#3000000
0%
#3010000
b10 ;
b100100 &
b100100 +
b10010110 )
1%
#3020000
0%
#3030000
b0 ;
b1010 :
b0 &
b0 +
b10010111 )
1%
#3040000
0%
#3050000
b1 ;
b10110111 &
b10110111 +
b10011000 )
1%
#3060000
0%
#3070000
b10 ;
b11101111 &
b11101111 +
b10011001 )
1%
#3080000
0%
#3090000
b0 ;
b1011 :
b0 &
b0 +
b10011010 )
1%
#3100000
0%
#3110000
b1 ;
b10110111 &
b10110111 +
b10011011 )
1%
#3120000
0%
#3130000
b10 ;
b11101111 &
b11101111 +
b10011100 )
1%
#3140000
0%
#3150000
b0 ;
b1100 :
b0 &
b0 +
b10011101 )
1%
#3160000
0%
#3170000
b1 ;
b10110111 &
b10110111 +
b10011110 )
1%
#3180000
0%
#3190000
b10 ;
b11101111 &
b11101111 +
b10011111 )
1%
#3200000
0%
#3210000
b0 ;
b1101 :
b0 &
b0 +
b10100000 )
1%
#3220000
0%
#3230000
b1 ;
b10110111 &
b10110111 +
b10100001 )
1%
#3240000
0%
#3250000
b10 ;
b11101111 &
b11101111 +
b10100010 )
1%
#3260000
0%
#3270000
b0 ;
b1110 :
b0 &
b0 +
b10100011 )
1%
#3280000
0%
#3290000
b1 ;
b10110111 &
b10110111 +
b10100100 )
1%
#3300000
0%
#3310000
b10 ;
b11101111 &
b11101111 +
b10100101 )
1%
#3320000
0%
#3330000
b0 ;
b1111 :
b1101111 &
b1101111 +
b10100110 )
1%
#3340000
0%
#3350000
b1 ;
b110001 &
b110001 +
b10100111 )
1%
#3360000
0%
#3370000
b10 ;
b10011000 &
b10011000 +
b10101000 )
1%
#3380000
0%
#3390000
b0 ;
b10000 :
b1101111 &
b1101111 +
b10101001 )
1%
#3400000
0%
#3410000
b1 ;
b110001 &
b110001 +
b10101010 )
1%
#3420000
0%
#3430000
b10 ;
b10011000 &
b10011000 +
b10101011 )
1%
#3440000
0%
#3450000
b0 ;
b10001 :
b11111111 &
b11111111 +
b10101100 )
1%
#3460000
0%
#3470000
b1 ;
b10100011 &
b10100011 +
b10101101 )
1%
#3480000
0%
#3490000
b10 ;
b10110001 &
b10110001 +
b10101110 )
1%
#3500000
0%
#3510000
b0 ;
b10010 :
b11111111 &
b11111111 +
b10101111 )
1%
#3520000
0%
#3530000
b1 ;
b10100011 &
b10100011 +
b10110000 )
1%
#3540000
0%
#3550000
b10 ;
b10110001 &
b10110001 +
b10110001 )
1%
#3560000
0%
#3570000
b0 ;
b10011 :
b11111111 &
b11111111 +
b10110010 )
1%
#3580000
0%
#3590000
b1 ;
b10100011 &
b10100011 +
b10110011 )
1%
#3600000
0%
#3610000
b10 ;
b10110001 &
b10110001 +
b10110100 )
1%
#3620000
0%
#3630000
b0 ;
b11 <
b0 :
b1001101 &
b1001101 +
b10110101 )
1%
#3640000
0%
#3650000
b1 ;
b1101101 &
b1101101 +
b10110110 )
1%
#3660000
0%
#3670000
b10 ;
b11110011 &
b11110011 +
b10110111 )
1%
#3680000
0%
#3690000
b0 ;
b1 :
b1001101 &
b1001101 +
b10111000 )
1%
#3700000
0%
#3710000
b1 ;
b1101101 &
b1101101 +
b10111001 )
1%
#3720000
0%
#3730000
b10 ;
b11110011 &
b11110011 +
b10111010 )
1%
#3740000
0%
#3750000
b0 ;
b10 :
b1001101 &
b1001101 +
b10111011 )
1%
#3760000
0%
#3770000
b1 ;
b1101101 &
b1101101 +
b10111100 )
1%
#3780000
0%
#3790000
b10 ;
b11110011 &
b11110011 +
b10111101 )
1%
#3800000
0%
#3810000
b0 ;
b11 :
b1101111 &
b1101111 +
b10111110 )
1%
#3820000
0%
#3830000
b1 ;
b110001 &
b110001 +
b10111111 )
1%
#3840000
0%
#3850000
b10 ;
b10011000 &
b10011000 +
b11000000 )
1%
#3860000
0%
#3870000
b0 ;
b100 :
b1101111 &
b1101111 +
b11000001 )
1%
#3880000
0%
#3890000
b1 ;
b110001 &
b110001 +
b11000010 )
1%
#3900000
0%
#3910000
b10 ;
b10011000 &
b10011000 +
b11000011 )
1%
#3920000
0%
#3930000
b0 ;
b101 :
b1101111 &
b1101111 +
b11000100 )
1%
#3940000
0%
#3950000
b1 ;
b110001 &
b110001 +
b11000101 )
1%
#3960000
0%
#3970000
b10 ;
b10011000 &
b10011000 +
b11000110 )
1%
#3980000
0%
#3990000
b0 ;
b110 :
b11101101 &
b11101101 +
b11000111 )
1%
#4000000
0%
#4010000
b1 ;
b11100 &
b11100 +
b11001000 )
1%
#4020000
0%
#4030000
b10 ;
b100100 &
b100100 +
b11001001 )
1%
#4040000
0%
#4050000
b0 ;
b111 :
b11101101 &
b11101101 +
b11001010 )
1%
#4060000
0%
#4070000
b1 ;
b11100 &
b11100 +
b11001011 )
1%
#4080000
0%
#4090000
b10 ;
b100100 &
b100100 +
b11001100 )
1%
#4100000
0%
#4110000
b0 ;
b1000 :
b11101101 &
b11101101 +
b11001101 )
1%
#4120000
0%
#4130000
b1 ;
b11100 &
b11100 +
b11001110 )
1%
#4140000
0%
#4150000
b10 ;
b100100 &
b100100 +
b11001111 )
1%
#4160000
0%
#4170000
b0 ;
b1001 :
b11101101 &
b11101101 +
b11010000 )
1%
#4180000
0%
#4190000
b1 ;
b11100 &
b11100 +
b11010001 )
1%
#4200000
0%
#4210000
b10 ;
b100100 &
b100100 +
b11010010 )
1%
#4220000
0%
#4230000
b0 ;
b1010 :
b0 &
b0 +
b11010011 )
1%
#4240000
0%
#4250000
b1 ;
b10110111 &
b10110111 +
b11010100 )
1%
#4260000
0%
#4270000
b10 ;
b11101111 &
b11101111 +
b11010101 )
1%
#4280000
0%
#4290000
b0 ;
b1011 :
b0 &
b0 +
b11010110 )
1%
#4300000
0%
#4310000
b1 ;
b10110111 &
b10110111 +
b11010111 )
1%
#4320000
0%
#4330000
b10 ;
b11101111 &
b11101111 +
b11011000 )
1%
#4340000
0%
#4350000
b0 ;
b1100 :
b0 &
b0 +
b11011001 )
1%
#4360000
0%
#4370000
b1 ;
b10110111 &
b10110111 +
b11011010 )
1%
#4380000
0%
#4390000
b10 ;
b11101111 &
b11101111 +
b11011011 )
1%
#4400000
0%
#4410000
b0 ;
b1101 :
b0 &
b0 +
b11011100 )
1%
#4420000
0%
#4430000
b1 ;
b10110111 &
b10110111 +
b11011101 )
1%
#4440000
0%
#4450000
b10 ;
b11101111 &
b11101111 +
b11011110 )
1%
#4460000
0%
#4470000
b0 ;
b1110 :
b1101111 &
b1101111 +
b11011111 )
1%
#4480000
0%
#4490000
b1 ;
b110001 &
b110001 +
b11100000 )
1%
#4500000
0%
#4510000
b10 ;
b10011000 &
b10011000 +
b11100001 )
1%
#4520000
0%
#4530000
b0 ;
b1111 :
b1101111 &
b1101111 +
b11100010 )
1%
#4540000
0%
#4550000
b1 ;
b110001 &
b110001 +
b11100011 )
1%
#4560000
0%
#4570000
b10 ;
b10011000 &
b10011000 +
b11100100 )
1%
#4580000
0%
#4590000
b0 ;
b10000 :
b1101111 &
b1101111 +
b11100101 )
1%
#4600000
0%
#4610000
b1 ;
b110001 &
b110001 +
b11100110 )
1%
#4620000
0%
#4630000
b10 ;
b10011000 &
b10011000 +
b11100111 )
1%
#4640000
0%
#4650000
b0 ;
b10001 :
b11111111 &
b11111111 +
b11101000 )
1%
#4660000
0%
#4670000
b1 ;
b10100011 &
b10100011 +
b11101001 )
1%
#4680000
0%
#4690000
b10 ;
b10110001 &
b10110001 +
b11101010 )
1%
#4700000
0%
#4710000
b0 ;
b10010 :
b11111111 &
b11111111 +
b11101011 )
1%
#4720000
0%
#4730000
b1 ;
b10100011 &
b10100011 +
b11101100 )
1%
#4740000
0%
#4750000
b10 ;
b10110001 &
b10110001 +
b11101101 )
1%
#4760000
0%
#4770000
b0 ;
b10011 :
b11111111 &
b11111111 +
b11101110 )
1%
#4780000
0%
#4790000
b1 ;
b10100011 &
b10100011 +
b11101111 )
1%
#4800000
0%
#4810000
b10 ;
b10110001 &
b10110001 +
b11110000 )
1%
#4820000
0%
#4830000
b0 ;
b100 <
b0 :
b1001101 &
b1001101 +
b11110001 )
1%
#4840000
0%
#4850000
b1 ;
b1101101 &
b1101101 +
b11110010 )
1%
#4860000
0%
#4870000
b10 ;
b11110011 &
b11110011 +
b11110011 )
1%
#4880000
0%
#4890000
b0 ;
b1 :
b1001101 &
b1001101 +
b11110100 )
1%
#4900000
0%
#4910000
b1 ;
b1101101 &
b1101101 +
b11110101 )
1%
#4920000
0%
#4930000
b10 ;
b11110011 &
b11110011 +
b11110110 )
1%
#4940000
0%
#4950000
b0 ;
b10 :
b1001101 &
b1001101 +
b11110111 )
1%
#4960000
0%
#4970000
b1 ;
b1101101 &
b1101101 +
b11111000 )
1%
#4980000
0%
#4990000
b10 ;
b11110011 &
b11110011 +
b11111001 )
1%
#5000000
0%
#5010000
b0 ;
b11 :
b1101111 &
b1101111 +
b11111010 )
1%
#5020000
0%
